LICENSE
MANIFEST.in
README.md
pyproject.toml
setup.py
nqe/__init__.py
nqe/_interp.pyx
nqe/interp.py
nqe/metrics.py
nqe/qnet.py
nqe/train.py
nqe.egg-info/PKG-INFO
nqe.egg-info/SOURCES.txt
nqe.egg-info/dependency_links.txt
nqe.egg-info/requires.txt
nqe.egg-info/top_level.txt