Metadata-Version: 2.1
Name: nqe
Version: 0.1.0.dev1
Summary: Neural Quantile Estimation.
Home-page: https://github.com/h3jia/nqe
Author: He Jia
Maintainer: He Jia
Maintainer-email: he.jia.phy@gmail.com
License: Apache License, Version 2.0
Requires-Python: >=3.7
License-File: LICENSE
